document_transformer/Document.py
document_transformer/Pipeline.py
document_transformer/Transformer.py
document_transformer/__init__.py
document_transformer/utils.py
document_transformer-0.1.5.dist-info/LICENSE
document_transformer-0.1.5.dist-info/METADATA
document_transformer-0.1.5.dist-info/WHEEL
document_transformer-0.1.5.dist-info/RECORD
