Metadata-Version: 2.1
Name: document-transformer
Version: 0.1.5
Summary: Organize your document transformation pipeline. Define your components, this tool ensure traceability and organization. Reuse your work easily in other projects
Home-page: https://github.com/johngonzalez/document-transformer
License: MIT
Keywords: document,transformer,pipeline,components,reuse,traceability,organization
Author: John Gonzalez
Author-email: johngonzalezv@gmail.com
Requires-Python: >=3.9,<4.0
Classifier: License :: OSI Approved :: MIT License
Classifier: Programming Language :: Python :: 3
Classifier: Programming Language :: Python :: 3.9
Classifier: Programming Language :: Python :: 3.10
Classifier: Programming Language :: Python :: 3.11
Classifier: Programming Language :: Python :: 3.12
Requires-Dist: graphviz (>=0.20.3,<0.21.0)
Requires-Dist: pydantic (>=2.7.2,<3.0.0)
Project-URL: Repository, https://github.com/johngonzalez/document-transformer
